devtools_user_agent/__init__.py
devtools_user_agent-1.0.1.dist-info/METADATA
devtools_user_agent-1.0.1.dist-info/WHEEL
devtools_user_agent-1.0.1.dist-info/top_level.txt
devtools_user_agent-1.0.1.dist-info/RECORD
