Metadata-Version: 2.1
Name: devtools-user-agent
Version: 1.0.1
Summary: User agent parser
Home-page: https://devtools.at/tools/user-agent-parser
Author: DevTools.at
Author-email: hello@devtools.at
Project-URL: Homepage, https://devtools.at/tools/user-agent-parser
Project-URL: Repository, https://github.com/devtools-at/user-agent-parser
Classifier: Development Status :: 4 - Beta
Classifier: Intended Audience :: Developers
Classifier: License :: OSI Approved :: MIT License
Classifier: Programming Language :: Python :: 3
Requires-Python: >=3.8
